[
  {
    "ContainingType": "project.Web.Controllers.ApiControllers.AdminController",
    "Method": "Dashboard",
    "RelativePath": "api/Admin/Dashboard",
    "HttpMethod": "GET",
    "IsController": true,
    "Order": 0,
    "Parameters": [],
    "ReturnTypes": []
  },
  {
    "ContainingType": "project.Web.Controllers.ApiControllers.AdminController",
    "Method": "PostManagement",
    "RelativePath": "api/Admin/PostManagement",
    "HttpMethod": "GET",
    "IsController": true,
    "Order": 0,
    "Parameters": [
      {
        "Name": "page",
        "Type": "System.Int32",
        "IsRequired": false
      },
      {
        "Name": "startDate",
        "Type": "System.DateTime",
        "IsRequired": false
      },
      {
        "Name": "endDate",
        "Type": "System.DateTime",
        "IsRequired": false
      }
    ],
    "ReturnTypes": [
      {
        "Type": "System.Collections.Generic.IEnumerable\u00601[[project.DAL.Entities.Post, project.DAL, Version=1.0.0.0, Culture=neutral, PublicKeyToken=null]]",
        "MediaTypes": [
          "text/plain",
          "application/json",
          "text/json"
        ],
        "StatusCode": 200
      }
    ]
  },
  {
    "ContainingType": "project.Web.Controllers.ApiControllers.AuthenticationController",
    "Method": "Login",
    "RelativePath": "api/Authentication/login",
    "HttpMethod": "POST",
    "IsController": true,
    "Order": 0,
    "Parameters": [
      {
        "Name": "model",
        "Type": "project.Web.Models.LoginViewModel",
        "IsRequired": true
      }
    ],
    "ReturnTypes": []
  },
  {
    "ContainingType": "project.Web.Controllers.ApiControllers.AuthenticationController",
    "Method": "Register",
    "RelativePath": "api/Authentication/register",
    "HttpMethod": "POST",
    "IsController": true,
    "Order": 0,
    "Parameters": [
      {
        "Name": "model",
        "Type": "project.Web.Models.RegisterViewModel",
        "IsRequired": true
      }
    ],
    "ReturnTypes": [
      {
        "Type": "project.common.Response.SingleResponse",
        "MediaTypes": [
          "text/plain",
          "application/json",
          "text/json"
        ],
        "StatusCode": 200
      }
    ]
  },
  {
    "ContainingType": "project.Web.Controllers.ApiControllers.BookmarkController",
    "Method": "BookmarkPost",
    "RelativePath": "api/Bookmark/BookmarkPost",
    "HttpMethod": "POST",
    "IsController": true,
    "Order": 0,
    "Parameters": [
      {
        "Name": "postId",
        "Type": "System.String",
        "IsRequired": false
      }
    ],
    "ReturnTypes": [
      {
        "Type": "System.Collections.Generic.IEnumerable\u00601[[System.String, System.Private.CoreLib, Version=6.0.0.0, Culture=neutral, PublicKeyToken=7cec85d7bea7798e]]",
        "MediaTypes": [
          "text/plain",
          "application/json",
          "text/json"
        ],
        "StatusCode": 200
      }
    ]
  },
  {
    "ContainingType": "project.Web.Controllers.ApiControllers.BookmarkController",
    "Method": "GetPostsIdsLikeByUser",
    "RelativePath": "api/Bookmark/GetPostIdsBookmarked",
    "HttpMethod": "GET",
    "IsController": true,
    "Order": 0,
    "Parameters": [],
    "ReturnTypes": [
      {
        "Type": "System.Collections.Generic.IEnumerable\u00601[[System.String, System.Private.CoreLib, Version=6.0.0.0, Culture=neutral, PublicKeyToken=7cec85d7bea7798e]]",
        "MediaTypes": [
          "text/plain",
          "application/json",
          "text/json"
        ],
        "StatusCode": 200
      }
    ]
  },
  {
    "ContainingType": "project.Web.Controllers.ApiControllers.BookmarkController",
    "Method": "UnlikePost",
    "RelativePath": "api/Bookmark/UnbookmarkPost",
    "HttpMethod": "POST",
    "IsController": true,
    "Order": 0,
    "Parameters": [
      {
        "Name": "postId",
        "Type": "System.String",
        "IsRequired": false
      }
    ],
    "ReturnTypes": [
      {
        "Type": "System.Nullable\u00601[[System.Int32, System.Private.CoreLib, Version=6.0.0.0, Culture=neutral, PublicKeyToken=7cec85d7bea7798e]]",
        "MediaTypes": [
          "text/plain",
          "application/json",
          "text/json"
        ],
        "StatusCode": 200
      }
    ]
  },
  {
    "ContainingType": "project.Web.Controllers.ApiControllers.BookmarkController",
    "Method": "UserbookmarkedPost",
    "RelativePath": "api/Bookmark/UserBookmarkedPost",
    "HttpMethod": "GET",
    "IsController": true,
    "Order": 0,
    "Parameters": [
      {
        "Name": "postId",
        "Type": "System.String",
        "IsRequired": false
      }
    ],
    "ReturnTypes": [
      {
        "Type": "System.Boolean",
        "MediaTypes": [
          "text/plain",
          "application/json",
          "text/json"
        ],
        "StatusCode": 200
      }
    ]
  },
  {
    "ContainingType": "project.Web.Controllers.ApiControllers.LikeController",
    "Method": "GetPostLikeCount",
    "RelativePath": "api/like/GetPostLikeCount",
    "HttpMethod": "GET",
    "IsController": true,
    "Order": 0,
    "Parameters": [
      {
        "Name": "postId",
        "Type": "System.String",
        "IsRequired": false
      }
    ],
    "ReturnTypes": [
      {
        "Type": "System.Nullable\u00601[[System.Int32, System.Private.CoreLib, Version=6.0.0.0, Culture=neutral, PublicKeyToken=7cec85d7bea7798e]]",
        "MediaTypes": [
          "text/plain",
          "application/json",
          "text/json"
        ],
        "StatusCode": 200
      }
    ]
  },
  {
    "ContainingType": "project.Web.Controllers.ApiControllers.LikeController",
    "Method": "LikePost",
    "RelativePath": "api/like/LikePost",
    "HttpMethod": "POST",
    "IsController": true,
    "Order": 0,
    "Parameters": [
      {
        "Name": "postId",
        "Type": "System.String",
        "IsRequired": false
      }
    ],
    "ReturnTypes": [
      {
        "Type": "System.Nullable\u00601[[System.Int32, System.Private.CoreLib, Version=6.0.0.0, Culture=neutral, PublicKeyToken=7cec85d7bea7798e]]",
        "MediaTypes": [
          "text/plain",
          "application/json",
          "text/json"
        ],
        "StatusCode": 200
      }
    ]
  },
  {
    "ContainingType": "project.Web.Controllers.ApiControllers.LikeController",
    "Method": "UnlikePost",
    "RelativePath": "api/like/UnlikePost",
    "HttpMethod": "POST",
    "IsController": true,
    "Order": 0,
    "Parameters": [
      {
        "Name": "postId",
        "Type": "System.String",
        "IsRequired": false
      }
    ],
    "ReturnTypes": [
      {
        "Type": "System.Nullable\u00601[[System.Int32, System.Private.CoreLib, Version=6.0.0.0, Culture=neutral, PublicKeyToken=7cec85d7bea7798e]]",
        "MediaTypes": [
          "text/plain",
          "application/json",
          "text/json"
        ],
        "StatusCode": 200
      }
    ]
  },
  {
    "ContainingType": "project.Web.Controllers.ApiControllers.LikeController",
    "Method": "UserLikedPost",
    "RelativePath": "api/like/UserLikedPost",
    "HttpMethod": "GET",
    "IsController": true,
    "Order": 0,
    "Parameters": [
      {
        "Name": "postId",
        "Type": "System.String",
        "IsRequired": false
      }
    ],
    "ReturnTypes": [
      {
        "Type": "System.Boolean",
        "MediaTypes": [
          "text/plain",
          "application/json",
          "text/json"
        ],
        "StatusCode": 200
      }
    ]
  },
  {
    "ContainingType": "project.Web.Controllers.ApiControllers.PostController",
    "Method": "AddComment",
    "RelativePath": "api/Post/AddComment",
    "HttpMethod": "POST",
    "IsController": true,
    "Order": 0,
    "Parameters": [
      {
        "Name": "model",
        "Type": "project.Web.Models.CommentInputModel",
        "IsRequired": true
      }
    ],
    "ReturnTypes": [
      {
        "Type": "project.DAL.Entities.Comment",
        "MediaTypes": [
          "text/plain",
          "application/json",
          "text/json"
        ],
        "StatusCode": 200
      }
    ]
  },
  {
    "ContainingType": "project.Web.Controllers.ApiControllers.PostController",
    "Method": "CreatePost",
    "RelativePath": "api/Post/CreatePost",
    "HttpMethod": "POST",
    "IsController": true,
    "Order": 0,
    "Parameters": [
      {
        "Name": "Description",
        "Type": "System.String",
        "IsRequired": false
      },
      {
        "Name": "MediaFile",
        "Type": "Microsoft.AspNetCore.Http.IFormFile",
        "IsRequired": false
      }
    ],
    "ReturnTypes": []
  },
  {
    "ContainingType": "project.Web.Controllers.ApiControllers.PostController",
    "Method": "DeleteMyPost",
    "RelativePath": "api/Post/deletePost",
    "HttpMethod": "DELETE",
    "IsController": true,
    "Order": 0,
    "Parameters": [
      {
        "Name": "postId",
        "Type": "System.String",
        "IsRequired": false
      }
    ],
    "ReturnTypes": []
  },
  {
    "ContainingType": "project.Web.Controllers.ApiControllers.PostController",
    "Method": "EditMyPost",
    "RelativePath": "api/Post/editPost",
    "HttpMethod": "PUT",
    "IsController": true,
    "Order": 0,
    "Parameters": [
      {
        "Name": "model",
        "Type": "project.Web.Models.CreatePostViewModel",
        "IsRequired": true
      },
      {
        "Name": "postId",
        "Type": "System.String",
        "IsRequired": false
      }
    ],
    "ReturnTypes": []
  },
  {
    "ContainingType": "project.Web.Controllers.ApiControllers.PostController",
    "Method": "GetAllPosts",
    "RelativePath": "api/Post/GetAllPosts",
    "HttpMethod": "GET",
    "IsController": true,
    "Order": 0,
    "Parameters": [],
    "ReturnTypes": [
      {
        "Type": "System.Collections.Generic.IEnumerable\u00601[[project.DAL.Entities.User, project.DAL, Version=1.0.0.0, Culture=neutral, PublicKeyToken=null]]",
        "MediaTypes": [
          "text/plain",
          "application/json",
          "text/json"
        ],
        "StatusCode": 200
      }
    ]
  },
  {
    "ContainingType": "project.Web.Controllers.ApiControllers.PostController",
    "Method": "GetAllPostsOfUser",
    "RelativePath": "api/Post/GetAllPostsOfUser",
    "HttpMethod": "GET",
    "IsController": true,
    "Order": 0,
    "Parameters": [],
    "ReturnTypes": [
      {
        "Type": "System.Collections.Generic.IEnumerable\u00601[[project.DAL.Entities.User, project.DAL, Version=1.0.0.0, Culture=neutral, PublicKeyToken=null]]",
        "MediaTypes": [
          "text/plain",
          "application/json",
          "text/json"
        ],
        "StatusCode": 200
      }
    ]
  },
  {
    "ContainingType": "project.Web.Controllers.ApiControllers.PostController",
    "Method": "GetAllCommentsOfPost",
    "RelativePath": "api/Post/GetCommentsOfPost",
    "HttpMethod": "GET",
    "IsController": true,
    "Order": 0,
    "Parameters": [
      {
        "Name": "postId",
        "Type": "System.String",
        "IsRequired": false
      }
    ],
    "ReturnTypes": [
      {
        "Type": "System.Collections.Generic.IEnumerable\u00601[[project.DAL.Entities.Comment, project.DAL, Version=1.0.0.0, Culture=neutral, PublicKeyToken=null]]",
        "MediaTypes": [
          "text/plain",
          "application/json",
          "text/json"
        ],
        "StatusCode": 200
      }
    ]
  },
  {
    "ContainingType": "project.Web.Controllers.ApiControllers.PostController",
    "Method": "GetPostById",
    "RelativePath": "api/Post/GetPostById",
    "HttpMethod": "GET",
    "IsController": true,
    "Order": 0,
    "Parameters": [
      {
        "Name": "postId",
        "Type": "System.String",
        "IsRequired": false
      }
    ],
    "ReturnTypes": [
      {
        "Type": "System.Collections.Generic.IEnumerable\u00601[[project.DAL.Entities.User, project.DAL, Version=1.0.0.0, Culture=neutral, PublicKeyToken=null]]",
        "MediaTypes": [
          "text/plain",
          "application/json",
          "text/json"
        ],
        "StatusCode": 200
      }
    ]
  },
  {
    "ContainingType": "project.Web.Controllers.ApiControllers.UserController",
    "Method": "GetAllUsersCount",
    "RelativePath": "api/User/GetAllUsersCount",
    "HttpMethod": "GET",
    "IsController": true,
    "Order": 0,
    "Parameters": [],
    "ReturnTypes": [
      {
        "Type": "System.Int32",
        "MediaTypes": [
          "text/plain",
          "application/json",
          "text/json"
        ],
        "StatusCode": 200
      }
    ]
  },
  {
    "ContainingType": "project.Web.Controllers.ApiControllers.UserController",
    "Method": "GetCurrentUser",
    "RelativePath": "api/User/GetCurrentUser",
    "HttpMethod": "GET",
    "IsController": true,
    "Order": 0,
    "Parameters": [],
    "ReturnTypes": [
      {
        "Type": "project.DAL.Entities.User",
        "MediaTypes": [
          "text/plain",
          "application/json",
          "text/json"
        ],
        "StatusCode": 200
      }
    ]
  },
  {
    "ContainingType": "project.Web.Controllers.ApiControllers.UserController",
    "Method": "GetFollowings",
    "RelativePath": "api/User/GetFollowings",
    "HttpMethod": "GET",
    "IsController": true,
    "Order": 0,
    "Parameters": [],
    "ReturnTypes": [
      {
        "Type": "System.Collections.Generic.IEnumerable\u00601[[project.DAL.Entities.User, project.DAL, Version=1.0.0.0, Culture=neutral, PublicKeyToken=null]]",
        "MediaTypes": [
          "text/plain",
          "application/json",
          "text/json"
        ],
        "StatusCode": 200
      }
    ]
  },
  {
    "ContainingType": "project.Web.Controllers.ApiControllers.UserController",
    "Method": "GetUsersByText",
    "RelativePath": "api/User/GetUsersByText",
    "HttpMethod": "GET",
    "IsController": true,
    "Order": 0,
    "Parameters": [
      {
        "Name": "search",
        "Type": "System.String",
        "IsRequired": false
      }
    ],
    "ReturnTypes": [
      {
        "Type": "System.Collections.Generic.IEnumerable\u00601[[project.Web.DTOs.UserDTO, project.Web, Version=1.0.0.0, Culture=neutral, PublicKeyToken=null]]",
        "MediaTypes": [
          "text/plain",
          "application/json",
          "text/json"
        ],
        "StatusCode": 200
      }
    ]
  },
  {
    "ContainingType": "project.Web.Controllers.ApiControllers.UserController",
    "Method": "UpdateProfileImage",
    "RelativePath": "api/User/UpdateProfileImage",
    "HttpMethod": "POST",
    "IsController": true,
    "Order": 0,
    "Parameters": [
      {
        "Name": "MediaFile",
        "Type": "Microsoft.AspNetCore.Http.IFormFile",
        "IsRequired": false
      }
    ],
    "ReturnTypes": []
  }
]